rlish/__init__.py
rlish/data_io.py
rlish-1.0.1.dist-info/LICENSE
rlish-1.0.1.dist-info/METADATA
rlish-1.0.1.dist-info/WHEEL
rlish-1.0.1.dist-info/RECORD
