Metadata-Version: 2.1
Name: rlish
Version: 1.0.1
Summary: 
Author: Andrew Garcia
Author-email: garcia.gtr@gmail.com
Requires-Python: >=3.10,<4.0
Classifier: Programming Language :: Python :: 3
Classifier: Programming Language :: Python :: 3.10
Classifier: Programming Language :: Python :: 3.11
Classifier: Programming Language :: Python :: 3.12
Requires-Dist: joblib (>=1.3.2,<2.0.0)
